{
	"name": "ChaoComFisica",
	"plugin-id": "TiledBg",
	"sid": 977575043592871,
	"isGlobal": false,
	"editorNewInstanceIsReplica": true,
	"instanceVariables": [],
	"behaviorTypes": [
		{
			"behaviorId": "solid",
			"name": "Sólido",
			"sid": 824125114343307
		}
	],
	"effectTypes": [],
	"image": {
		"width": 576,
		"height": 74,
		"originX": 0.5,
		"originY": 0.5,
		"originalSource": "",
		"exportFormat": "lossless",
		"exportQuality": 0.8,
		"fileType": "image/png",
		"imageSpriteId": 8817203,
		"useCollisionPoly": true,
		"tag": ""
	}
}